<annotation>
	<folder>videos</folder>
	<filename>5172_POV-Great_Northern_2020_Quals_22.mp4_00480.png</filename>
	<path>/home/ubuntu/tensorflow_workspace/2020Game/data/videos/5172_POV-Great_Northern_2020_Quals_22.mp4_00480.png</path>
	<source>
		<database>Unknown</database>
	</source>
	<size>
		<width>1280</width>
		<height>720</height>
		<depth>3</depth>
	</size>
	<segmented>0</segmented>
	<object>
		<name>blue_power_port_first_logo</name>
		<pose>Unspecified</pose>
		<truncated>0</truncated>
		<difficult>0</difficult>
		<bndbox>
			<xmin>535</xmin>
			<ymin>321</ymin>
			<xmax>553</xmax>
			<ymax>336</ymax>
		</bndbox>
	</object>
	<object>
		<name>blue_power_port_first_logo</name>
		<pose>Unspecified</pose>
		<truncated>0</truncated>
		<difficult>0</difficult>
		<bndbox>
			<xmin>430</xmin>
			<ymin>320</ymin>
			<xmax>453</xmax>
			<ymax>336</ymax>
		</bndbox>
	</object>
	<object>
		<name>power_port_yellow_graphics</name>
		<pose>Unspecified</pose>
		<truncated>0</truncated>
		<difficult>0</difficult>
		<bndbox>
			<xmin>471</xmin>
			<ymin>360</ymin>
			<xmax>514</xmax>
			<ymax>386</ymax>
		</bndbox>
	</object>
	<object>
		<name>blue_power_port_high_goal</name>
		<pose>Unspecified</pose>
		<truncated>0</truncated>
		<difficult>0</difficult>
		<bndbox>
			<xmin>469</xmin>
			<ymin>290</ymin>
			<xmax>526</xmax>
			<ymax>337</ymax>
		</bndbox>
	</object>
	<object>
		<name>blue_power_port_low_goal</name>
		<pose>Unspecified</pose>
		<truncated>0</truncated>
		<difficult>0</difficult>
		<bndbox>
			<xmin>455</xmin>
			<ymin>399</ymin>
			<xmax>527</xmax>
			<ymax>435</ymax>
		</bndbox>
	</object>
	<object>
		<name>power_cell</name>
		<pose>Unspecified</pose>
		<truncated>0</truncated>
		<difficult>0</difficult>
		<bndbox>
			<xmin>529</xmin>
			<ymin>455</ymin>
			<xmax>549</xmax>
			<ymax>476</ymax>
		</bndbox>
	</object>
	<object>
		<name>blue_tape_corner</name>
		<pose>Unspecified</pose>
		<truncated>0</truncated>
		<difficult>0</difficult>
		<bndbox>
			<xmin>465</xmin>
			<ymin>491</ymin>
			<xmax>487</xmax>
			<ymax>506</ymax>
		</bndbox>
	</object>
	<object>
		<name>shield_generator_yellow_stripe</name>
		<pose>Unspecified</pose>
		<truncated>0</truncated>
		<difficult>0</difficult>
		<bndbox>
			<xmin>240</xmin>
			<ymin>132</ymin>
			<xmax>279</xmax>
			<ymax>160</ymax>
		</bndbox>
	</object>
	<object>
		<name>shield_generator_first_logo</name>
		<pose>Unspecified</pose>
		<truncated>0</truncated>
		<difficult>0</difficult>
		<bndbox>
			<xmin>237</xmin>
			<ymin>71</ymin>
			<xmax>250</xmax>
			<ymax>99</ymax>
		</bndbox>
	</object>
	<object>
		<name>ds_numbers</name>
		<pose>Unspecified</pose>
		<truncated>0</truncated>
		<difficult>0</difficult>
		<bndbox>
			<xmin>364</xmin>
			<ymin>339</ymin>
			<xmax>397</xmax>
			<ymax>350</ymax>
		</bndbox>
	</object>
	<object>
		<name>ds_numbers</name>
		<pose>Unspecified</pose>
		<truncated>0</truncated>
		<difficult>0</difficult>
		<bndbox>
			<xmin>416</xmin>
			<ymin>341</ymin>
			<xmax>453</xmax>
			<ymax>354</ymax>
		</bndbox>
	</object>
	<object>
		<name>ds_numbers</name>
		<pose>Unspecified</pose>
		<truncated>0</truncated>
		<difficult>0</difficult>
		<bndbox>
			<xmin>541</xmin>
			<ymin>341</ymin>
			<xmax>568</xmax>
			<ymax>353</ymax>
		</bndbox>
	</object>
	<object>
		<name>red_ds_light</name>
		<pose>Unspecified</pose>
		<truncated>0</truncated>
		<difficult>0</difficult>
		<bndbox>
			<xmin>401</xmin>
			<ymin>339</ymin>
			<xmax>408</xmax>
			<ymax>354</ymax>
		</bndbox>
	</object>
	<object>
		<name>red_ds_light</name>
		<pose>Unspecified</pose>
		<truncated>0</truncated>
		<difficult>0</difficult>
		<bndbox>
			<xmin>582</xmin>
			<ymin>341</ymin>
			<xmax>587</xmax>
			<ymax>355</ymax>
		</bndbox>
	</object>
</annotation>
