<annotation verified="yes">
	<folder>videos</folder>
	<filename>powercell_29d9ea7d-9294-48fd-8b66-4d92cab891c6.png</filename>
	<path>/home/ubuntu/tensorflow_workspace/2020Game/data/videos/powercell_29d9ea7d-9294-48fd-8b66-4d92cab891c6.png</path>
	<source>
		<database>Unknown</database>
	</source>
	<size>
		<width>1280</width>
		<height>720</height>
		<depth>3</depth>
	</size>
	<segmented>0</segmented>
	<object>
		<name>power_cell</name>
		<pose>Unspecified</pose>
		<truncated>0</truncated>
		<difficult>0</difficult>
		<bndbox>
			<xmin>675</xmin>
			<ymin>270</ymin>
			<xmax>730</xmax>
			<ymax>328</ymax>
		</bndbox>
	</object>
</annotation>
