<annotation verified="yes">
	<folder>videos</folder>
	<filename>field_calibration_mapping_2024-03-16-12-59-52.avi_00019.png</filename>
	<path>/home/ubuntu/.tensorflow_workspace.readonly/2024Game/data/videos/field_calibration_mapping_2024-03-16-12-59-52.avi_00019.png</path>
	<source>
		<database>Unknown</database>
	</source>
	<size>
		<width>1104</width>
		<height>620</height>
		<depth>3</depth>
	</size>
	<segmented>0</segmented>
	<object>
		<name>note</name>
		<pose>Unspecified</pose>
		<truncated>0</truncated>
		<difficult>0</difficult>
		<bndbox>
			<xmin>438</xmin>
			<ymin>482</ymin>
			<xmax>576</xmax>
			<ymax>544</ymax>
		</bndbox>
	</object>
	<object>
		<name>note</name>
		<pose>Unspecified</pose>
		<truncated>0</truncated>
		<difficult>0</difficult>
		<bndbox>
			<xmin>44</xmin>
			<ymin>424</ymin>
			<xmax>200</xmax>
			<ymax>474</ymax>
		</bndbox>
	</object>
	<object>
		<name>red_tape_to_wall</name>
		<pose>Unspecified</pose>
		<truncated>0</truncated>
		<difficult>0</difficult>
		<bndbox>
			<xmin>521</xmin>
			<ymin>459</ymin>
			<xmax>557</xmax>
			<ymax>485</ymax>
		</bndbox>
	</object>
	<object>
		<name>red_tape_corner</name>
		<pose>Unspecified</pose>
		<truncated>0</truncated>
		<difficult>0</difficult>
		<bndbox>
			<xmin>52</xmin>
			<ymin>395</ymin>
			<xmax>90</xmax>
			<ymax>422</ymax>
		</bndbox>
	</object>
	<object>
		<name>red_tape_to_wall</name>
		<pose>Unspecified</pose>
		<truncated>0</truncated>
		<difficult>0</difficult>
		<bndbox>
			<xmin>90</xmin>
			<ymin>377</ymin>
			<xmax>123</xmax>
			<ymax>402</ymax>
		</bndbox>
	</object>
</annotation>
