<annotation verified="yes">
	<folder>videos</folder>
	<filename>FRC4481 - 2024 Prototypes - TR-Xs MAXswerve Driving Over Notes.mp4_00727.png</filename>
	<path>/Users/shauryabhatt/tensorflow_workspace/2024Game/data/videos/FRC4481 - 2024 Prototypes - TR-Xs MAXswerve Driving Over Notes.mp4_00727.png</path>
	<source>
		<database>Unknown</database>
	</source>
	<size>
		<width>1280</width>
		<height>720</height>
		<depth>3</depth>
	</size>
	<segmented>0</segmented>
	<object>
		<name>note</name>
		<pose>Unspecified</pose>
		<truncated>0</truncated>
		<difficult>0</difficult>
		<bndbox>
			<xmin>584</xmin>
			<ymin>593</ymin>
			<xmax>672</xmax>
			<ymax>622</ymax>
		</bndbox>
	</object>
	<object>
		<name>note</name>
		<pose>Unspecified</pose>
		<truncated>1</truncated>
		<difficult>0</difficult>
		<bndbox>
			<xmin>657</xmin>
			<ymin>671</ymin>
			<xmax>784</xmax>
			<ymax>720</ymax>
		</bndbox>
	</object>
</annotation>
