<annotation verified="yes">
	<folder>videos</folder>
	<filename>ncash_practice.mp4_07942.png</filename>
	<path>/home/ubuntu/.tensorflow_workspace.readonly/2024Game/data/videos/ncash_practice.mp4_07942.png</path>
	<source>
		<database>Unknown</database>
	</source>
	<size>
		<width>1920</width>
		<height>1080</height>
		<depth>3</depth>
	</size>
	<segmented>0</segmented>
	<object>
		<name>red_ds_light</name>
		<pose>Unspecified</pose>
		<truncated>0</truncated>
		<difficult>0</difficult>
		<bndbox>
			<xmin>210</xmin>
			<ymin>109</ymin>
			<xmax>235</xmax>
			<ymax>159</ymax>
		</bndbox>
	</object>
	<object>
		<name>red_ds_number</name>
		<pose>Unspecified</pose>
		<truncated>0</truncated>
		<difficult>0</difficult>
		<bndbox>
			<xmin>267</xmin>
			<ymin>107</ymin>
			<xmax>349</xmax>
			<ymax>148</ymax>
		</bndbox>
	</object>
	<object>
		<name>blue_tape_to_wall</name>
		<pose>Unspecified</pose>
		<truncated>0</truncated>
		<difficult>0</difficult>
		<bndbox>
			<xmin>343</xmin>
			<ymin>473</ymin>
			<xmax>370</xmax>
			<ymax>495</ymax>
		</bndbox>
	</object>
	<object>
		<name>blue_tape_to_wall</name>
		<pose>Unspecified</pose>
		<truncated>0</truncated>
		<difficult>0</difficult>
		<bndbox>
			<xmin>783</xmin>
			<ymin>426</ymin>
			<xmax>814</xmax>
			<ymax>449</ymax>
		</bndbox>
	</object>
	<object>
		<name>blue_tape_corner</name>
		<pose>Unspecified</pose>
		<truncated>0</truncated>
		<difficult>0</difficult>
		<bndbox>
			<xmin>731</xmin>
			<ymin>446</ymin>
			<xmax>765</xmax>
			<ymax>461</ymax>
		</bndbox>
	</object>
	<object>
		<name>note</name>
		<pose>Unspecified</pose>
		<truncated>0</truncated>
		<difficult>0</difficult>
		<bndbox>
			<xmin>617</xmin>
			<ymin>437</ymin>
			<xmax>697</xmax>
			<ymax>460</ymax>
		</bndbox>
	</object>
	<object>
		<name>note</name>
		<pose>Unspecified</pose>
		<truncated>0</truncated>
		<difficult>0</difficult>
		<bndbox>
			<xmin>404</xmin>
			<ymin>457</ymin>
			<xmax>477</xmax>
			<ymax>485</ymax>
		</bndbox>
	</object>
</annotation>
