<annotation>
	<folder>videos</folder>
	<filename>y2mate.is - 2024 Field Tour Video Speaker-XOdxXNeCXKQ-1080pp-1705155694.mp4_01507.png</filename>
	<path>/home/ubuntu/tensorflow_workspace/2024Game/data/videos/y2mate.is - 2024 Field Tour Video Speaker-XOdxXNeCXKQ-1080pp-1705155694.mp4_01507.png</path>
	<source>
		<database>Unknown</database>
	</source>
	<size>
		<width>1920</width>
		<height>1080</height>
		<depth>3</depth>
	</size>
	<segmented>0</segmented>
	<object>
		<name>red_triangle_text</name>
		<pose>Unspecified</pose>
		<truncated>0</truncated>
		<difficult>0</difficult>
		<bndbox>
			<xmin>1579</xmin>
			<ymin>187</ymin>
			<xmax>1608</xmax>
			<ymax>341</ymax>
		</bndbox>
	</object>
	<object>
		<name>red_triangle_text</name>
		<pose>Unspecified</pose>
		<truncated>0</truncated>
		<difficult>0</difficult>
		<bndbox>
			<xmin>806</xmin>
			<ymin>121</ymin>
			<xmax>964</xmax>
			<ymax>243</ymax>
		</bndbox>
	</object>
	<object>
		<name>crescendo_logo</name>
		<pose>Unspecified</pose>
		<truncated>0</truncated>
		<difficult>0</difficult>
		<bndbox>
			<xmin>486</xmin>
			<ymin>695</ymin>
			<xmax>628</xmax>
			<ymax>747</ymax>
		</bndbox>
	</object>
	<object>
		<name>crescendo_logo</name>
		<pose>Unspecified</pose>
		<truncated>0</truncated>
		<difficult>0</difficult>
		<bndbox>
			<xmin>1411</xmin>
			<ymin>585</ymin>
			<xmax>1475</xmax>
			<ymax>649</ymax>
		</bndbox>
	</object>
	<object>
		<name>blue_ds_number</name>
		<pose>Unspecified</pose>
		<truncated>0</truncated>
		<difficult>0</difficult>
		<bndbox>
			<xmin>921</xmin>
			<ymin>251</ymin>
			<xmax>1077</xmax>
			<ymax>321</ymax>
		</bndbox>
	</object>
	<object>
		<name>blue_ds_number</name>
		<pose>Unspecified</pose>
		<truncated>0</truncated>
		<difficult>0</difficult>
		<bndbox>
			<xmin>1603</xmin>
			<ymin>380</ymin>
			<xmax>1631</xmax>
			<ymax>444</ymax>
		</bndbox>
	</object>
	<object>
		<name>red_ds_number</name>
		<pose>Unspecified</pose>
		<truncated>0</truncated>
		<difficult>0</difficult>
		<bndbox>
			<xmin>1677</xmin>
			<ymin>521</ymin>
			<xmax>1708</xmax>
			<ymax>581</ymax>
		</bndbox>
	</object>
	<object>
		<name>red_ds_light</name>
		<pose>Unspecified</pose>
		<truncated>0</truncated>
		<difficult>0</difficult>
		<bndbox>
			<xmin>1650</xmin>
			<ymin>458</ymin>
			<xmax>1667</xmax>
			<ymax>500</ymax>
		</bndbox>
	</object>
</annotation>
