<annotation>
    <folder>train</folder>
    <filename>Img-2636_mp4-9_jpg.rf.aad26105aba3103499f8b4d3a7f37c11.jpg</filename>
    <path>/home/ubuntu/tensorflow_workspace/2024Game/data/FRC2024/train/Img-2636_mp4-9_jpg.rf.aad26105aba3103499f8b4d3a7f37c11.jpg</path>
    <source>
        <database>Unknown</database>
    </source>
    <size>
        <width>640</width>
        <height>640</height>
        <depth>3</depth>
    </size>
    <segmented>0</segmented>
    <object>
        <name>note</name>
        <pose>Unspecified</pose>
        <truncated>0</truncated>
        <difficult>0</difficult>
        <bndbox>
            <xmin>316</xmin>
            <ymin>259</ymin>
            <xmax>376.73</xmax>
            <ymax>327.688</ymax>
        </bndbox>
    </object>    <object>
        <name>note</name>
        <pose>Unspecified</pose>
        <truncated>0</truncated>
        <difficult>0</difficult>
        <bndbox>
            <xmin>274</xmin>
            <ymin>217</ymin>
            <xmax>318.874</xmax>
            <ymax>264.251</ymax>
        </bndbox>
    </object>    <object>
        <name>note</name>
        <pose>Unspecified</pose>
        <truncated>0</truncated>
        <difficult>0</difficult>
        <bndbox>
            <xmin>243</xmin>
            <ymin>204</ymin>
            <xmax>289.915</xmax>
            <ymax>252.309</ymax>
        </bndbox>
    </object>    <object>
        <name>note</name>
        <pose>Unspecified</pose>
        <truncated>0</truncated>
        <difficult>0</difficult>
        <bndbox>
            <xmin>171</xmin>
            <ymin>246</ymin>
            <xmax>222.078</xmax>
            <ymax>298.426</ymax>
        </bndbox>
    </object>
</annotation>
