<annotation>
    <folder>train</folder>
    <filename>Img-2572_mp4-24_jpg.rf.ececf6feaa1fc0a08d0557c3d0c03f37.jpg</filename>
    <path>/home/ubuntu/tensorflow_workspace/2024Game/data/FRC2024/train/Img-2572_mp4-24_jpg.rf.ececf6feaa1fc0a08d0557c3d0c03f37.jpg</path>
    <source>
        <database>Unknown</database>
    </source>
    <size>
        <width>640</width>
        <height>640</height>
        <depth>3</depth>
    </size>
    <segmented>0</segmented>
    <object>
        <name>note</name>
        <pose>Unspecified</pose>
        <truncated>0</truncated>
        <difficult>0</difficult>
        <bndbox>
            <xmin>187</xmin>
            <ymin>0</ymin>
            <xmax>411</xmax>
            <ymax>560</ymax>
        </bndbox>
    </object>
</annotation>
