<annotation>
    <folder>train</folder>
    <filename>Img-2618_mp4-22_jpg.rf.aa62619301402901ac5bf1d43b608792.jpg</filename>
    <path>/home/ubuntu/tensorflow_workspace/2024Game/data/FRC2024/train/Img-2618_mp4-22_jpg.rf.aa62619301402901ac5bf1d43b608792.jpg</path>
    <source>
        <database>Unknown</database>
    </source>
    <size>
        <width>640</width>
        <height>640</height>
        <depth>3</depth>
    </size>
    <segmented>0</segmented>
    <object>
        <name>note</name>
        <pose>Unspecified</pose>
        <truncated>0</truncated>
        <difficult>0</difficult>
        <bndbox>
            <xmin>133</xmin>
            <ymin>426</ymin>
            <xmax>386.46000000000004</xmax>
            <ymax>640.034</ymax>
        </bndbox>
    </object>    <object>
        <name>note</name>
        <pose>Unspecified</pose>
        <truncated>0</truncated>
        <difficult>0</difficult>
        <bndbox>
            <xmin>236</xmin>
            <ymin>56</ymin>
            <xmax>332.24</xmax>
            <ymax>137.926</ymax>
        </bndbox>
    </object>
</annotation>
