<annotation>
    <folder>train</folder>
    <filename>youtube-0_jpg.rf.a8fac4bd1f8e32683a438077390faf6c.jpg</filename>
    <path>/home/ubuntu/tensorflow_workspace/2024Game/data/FRC2024/train/youtube-0_jpg.rf.a8fac4bd1f8e32683a438077390faf6c.jpg</path>
    <source>
        <database>Unknown</database>
    </source>
    <size>
        <width>640</width>
        <height>640</height>
        <depth>3</depth>
    </size>
    <segmented>0</segmented>
    <object>
        <name>note</name>
        <pose>Unspecified</pose>
        <truncated>0</truncated>
        <difficult>0</difficult>
        <bndbox>
            <xmin>196</xmin>
            <ymin>160</ymin>
            <xmax>401</xmax>
            <ymax>464</ymax>
        </bndbox>
    </object>
</annotation>
