<annotation>
    <folder>FRC2024</folder>
    <filename>youtube-298_jpg.rf.e5184cdc3e80141e8d1631e67373e6ce.jpg</filename>
    <path>/home/ubuntu/tensorflow_workspace/2024Game/data/FRC2024/youtube-298_jpg.rf.e5184cdc3e80141e8d1631e67373e6ce.jpg</path>
    <source>
        <database>Unknown</database>
    </source>
    <size>
        <width>640</width>
        <height>640</height>
        <depth>3</depth>
    </size>
    <segmented>0</segmented>
    <object>
        <name>note</name>
        <pose>Unspecified</pose>
        <truncated>0</truncated>
        <difficult>0</difficult>
        <bndbox>
            <xmin>116</xmin>
            <ymin>307</ymin>
            <xmax>228</xmax>
            <ymax>451</ymax>
        </bndbox>
    </object>    <object>
        <name>note</name>
        <pose>Unspecified</pose>
        <truncated>0</truncated>
        <difficult>0</difficult>
        <bndbox>
            <xmin>348</xmin>
            <ymin>267</ymin>
            <xmax>456</xmax>
            <ymax>383.5</ymax>
        </bndbox>
    </object>    <object>
        <name>note</name>
        <pose>Unspecified</pose>
        <truncated>0</truncated>
        <difficult>0</difficult>
        <bndbox>
            <xmin>339</xmin>
            <ymin>286</ymin>
            <xmax>434.5</xmax>
            <ymax>411</ymax>
        </bndbox>
    </object>
</annotation>
