<annotation>
    <folder>FRC2024</folder>
    <filename>youtube-32_jpg.rf.a9cfc0e8fd6a14ac206b5635d5d70377.jpg</filename>
    <path>/home/ubuntu/tensorflow_workspace/2024Game/data/FRC2024/youtube-32_jpg.rf.a9cfc0e8fd6a14ac206b5635d5d70377.jpg</path>
    <source>
        <database>Unknown</database>
    </source>
    <size>
        <width>640</width>
        <height>640</height>
        <depth>3</depth>
    </size>
    <segmented>0</segmented>
    <object>
        <name>note</name>
        <pose>Unspecified</pose>
        <truncated>0</truncated>
        <difficult>0</difficult>
        <bndbox>
            <xmin>218</xmin>
            <ymin>232</ymin>
            <xmax>383.624</xmax>
            <ymax>462.20799999999997</ymax>
        </bndbox>
    </object>
</annotation>
