<annotation>
    <folder>FRC2024</folder>
    <filename>youtube-63_jpg.rf.d43bb88998ce9fd5ec44282e6db15b6d.jpg</filename>
    <path>/home/ubuntu/tensorflow_workspace/2024Game/data/FRC2024/youtube-63_jpg.rf.d43bb88998ce9fd5ec44282e6db15b6d.jpg</path>
    <source>
        <database>Unknown</database>
    </source>
    <size>
        <width>640</width>
        <height>640</height>
        <depth>3</depth>
    </size>
    <segmented>0</segmented>
    <object>
        <name>note</name>
        <pose>Unspecified</pose>
        <truncated>0</truncated>
        <difficult>0</difficult>
        <bndbox>
            <xmin>175</xmin>
            <ymin>164</ymin>
            <xmax>402.5</xmax>
            <ymax>358.44399999999996</ymax>
        </bndbox>
    </object>
</annotation>
