<annotation verified="yes">
	<folder>apriltag_videos</folder>
	<filename>IMG_6395.MOV_01002.png</filename>
	<path>/home/ubuntu/tensorflow_workspace/2023Game/data/apriltag_videos/IMG_6395.MOV_01002.png</path>
	<source>
		<database>Unknown</database>
	</source>
	<size>
		<width>1920</width>
		<height>1080</height>
		<depth>3</depth>
	</size>
	<segmented>0</segmented>
	<object>
		<name>april_tag_7</name>
		<pose>Unspecified</pose>
		<truncated>0</truncated>
		<difficult>0</difficult>
		<bndbox>
			<xmin>886</xmin>
			<ymin>579</ymin>
			<xmax>934</xmax>
			<ymax>617</ymax>
		</bndbox>
	</object>
	<object>
		<name>april_tag_8</name>
		<pose>Unspecified</pose>
		<truncated>0</truncated>
		<difficult>0</difficult>
		<bndbox>
			<xmin>963</xmin>
			<ymin>594</ymin>
			<xmax>1013</xmax>
			<ymax>639</ymax>
		</bndbox>
	</object>
	<object>
		<name>blue_robot</name>
		<pose>Unspecified</pose>
		<truncated>0</truncated>
		<difficult>0</difficult>
		<bndbox>
			<xmin>1568</xmin>
			<ymin>683</ymin>
			<xmax>1806</xmax>
			<ymax>996</ymax>
		</bndbox>
	</object>
</annotation>
