<annotation>
    <folder>FRC2024</folder>
    <filename>20240108_012214_mp4-95_jpg.rf.ada6f4998a35b398c9eb365cfabbdc57.jpg</filename>
    <path>/home/ubuntu/tensorflow_workspace/2024Game/data/FRC2024/20240108_012214_mp4-95_jpg.rf.ada6f4998a35b398c9eb365cfabbdc57.jpg</path>
    <source>
        <database>Unknown</database>
    </source>
    <size>
        <width>960</width>
        <height>960</height>
        <depth>3</depth>
    </size>
    <segmented>0</segmented>
    <object>
        <name>note</name>
        <pose>Unspecified</pose>
        <truncated>0</truncated>
        <difficult>0</difficult>
        <bndbox>
            <xmin>300</xmin>
            <ymin>383</ymin>
            <xmax>553.235</xmax>
            <ymax>770.381</ymax>
        </bndbox>
    </object>
</annotation>
