<annotation>
    <folder>FRC2024</folder>
    <filename>21_jpg.rf.5104e41ebf949d6196a2dbc220a7de22.jpg</filename>
    <path>/home/ubuntu/tensorflow_workspace/2024Game/data/FRC2024/21_jpg.rf.5104e41ebf949d6196a2dbc220a7de22.jpg</path>
    <source>
        <database>Unknown</database>
    </source>
    <size>
        <width>640</width>
        <height>640</height>
        <depth>3</depth>
    </size>
    <segmented>0</segmented>
    <object>
        <name>note</name>
        <pose>Unspecified</pose>
        <truncated>0</truncated>
        <difficult>0</difficult>
        <bndbox>
            <xmin>256</xmin>
            <ymin>155</ymin>
            <xmax>341.741</xmax>
            <ymax>255.46800000000002</ymax>
        </bndbox>
    </object>
</annotation>
