<annotation>
    <folder>FRC2024</folder>
    <filename>Img-2627_mp4-2_jpg.rf.c40f81118c7ea9317cdb3d585e6d11a9.jpg</filename>
    <path>/home/ubuntu/tensorflow_workspace/2024Game/data/FRC2024/Img-2627_mp4-2_jpg.rf.c40f81118c7ea9317cdb3d585e6d11a9.jpg</path>
    <source>
        <database>Unknown</database>
    </source>
    <size>
        <width>640</width>
        <height>640</height>
        <depth>3</depth>
    </size>
    <segmented>0</segmented>
    <object>
        <name>note</name>
        <pose>Unspecified</pose>
        <truncated>0</truncated>
        <difficult>0</difficult>
        <bndbox>
            <xmin>19</xmin>
            <ymin>0</ymin>
            <xmax>153.667</xmax>
            <ymax>89.197</ymax>
        </bndbox>
    </object>    <object>
        <name>note</name>
        <pose>Unspecified</pose>
        <truncated>0</truncated>
        <difficult>0</difficult>
        <bndbox>
            <xmin>66</xmin>
            <ymin>0</ymin>
            <xmax>259.35699999999997</xmax>
            <ymax>158.468</ymax>
        </bndbox>
    </object>    <object>
        <name>note</name>
        <pose>Unspecified</pose>
        <truncated>0</truncated>
        <difficult>0</difficult>
        <bndbox>
            <xmin>148</xmin>
            <ymin>84</ymin>
            <xmax>369.472</xmax>
            <ymax>348.368</ymax>
        </bndbox>
    </object>
</annotation>
