<annotation>
    <folder>FRC2024</folder>
    <filename>Img-2568_mp4-44_jpg.rf.027b44fdca425cc89dfeb61bc7ebbdc0.jpg</filename>
    <path>/home/ubuntu/tensorflow_workspace/2024Game/data/FRC2024/Img-2568_mp4-44_jpg.rf.027b44fdca425cc89dfeb61bc7ebbdc0.jpg</path>
    <source>
        <database>Unknown</database>
    </source>
    <size>
        <width>640</width>
        <height>640</height>
        <depth>3</depth>
    </size>
    <segmented>0</segmented>
    <object>
        <name>note</name>
        <pose>Unspecified</pose>
        <truncated>0</truncated>
        <difficult>0</difficult>
        <bndbox>
            <xmin>130</xmin>
            <ymin>278</ymin>
            <xmax>223.5</xmax>
            <ymax>383.5</ymax>
        </bndbox>
    </object>
</annotation>
