<annotation>
    <folder>FRC2024</folder>
    <filename>Img-2619_mp4-1_jpg.rf.e018e9a404ff84aeee36cc4d97ed3e1f.jpg</filename>
    <path>/home/ubuntu/tensorflow_workspace/2024Game/data/FRC2024/Img-2619_mp4-1_jpg.rf.e018e9a404ff84aeee36cc4d97ed3e1f.jpg</path>
    <source>
        <database>Unknown</database>
    </source>
    <size>
        <width>640</width>
        <height>640</height>
        <depth>3</depth>
    </size>
    <segmented>0</segmented>
    <object>
        <name>note</name>
        <pose>Unspecified</pose>
        <truncated>0</truncated>
        <difficult>0</difficult>
        <bndbox>
            <xmin>301</xmin>
            <ymin>514</ymin>
            <xmax>361.5</xmax>
            <ymax>579</ymax>
        </bndbox>
    </object>    <object>
        <name>note</name>
        <pose>Unspecified</pose>
        <truncated>0</truncated>
        <difficult>0</difficult>
        <bndbox>
            <xmin>277</xmin>
            <ymin>364</ymin>
            <xmax>317</xmax>
            <ymax>397.5</ymax>
        </bndbox>
    </object>    <object>
        <name>note</name>
        <pose>Unspecified</pose>
        <truncated>0</truncated>
        <difficult>0</difficult>
        <bndbox>
            <xmin>267</xmin>
            <ymin>273</ymin>
            <xmax>295</xmax>
            <ymax>293.5</ymax>
        </bndbox>
    </object>
</annotation>
