<annotation>
    <folder>FRC2024</folder>
    <filename>Img-2602_mp4-31_jpg.rf.f7b191458b56930d9db7db22a380adf9.jpg</filename>
    <path>/home/ubuntu/tensorflow_workspace/2024Game/data/FRC2024/Img-2602_mp4-31_jpg.rf.f7b191458b56930d9db7db22a380adf9.jpg</path>
    <source>
        <database>Unknown</database>
    </source>
    <size>
        <width>640</width>
        <height>640</height>
        <depth>3</depth>
    </size>
    <segmented>0</segmented>
    <object>
        <name>note</name>
        <pose>Unspecified</pose>
        <truncated>0</truncated>
        <difficult>0</difficult>
        <bndbox>
            <xmin>628</xmin>
            <ymin>243</ymin>
            <xmax>640</xmax>
            <ymax>375.14</ymax>
        </bndbox>
    </object>
</annotation>
