<annotation>
    <folder>FRC2024</folder>
    <filename>Img-2596_mp4-18_jpg.rf.0863202bddb508751af5634bd9fa0cc6.jpg</filename>
    <path>/home/ubuntu/tensorflow_workspace/2024Game/data/FRC2024/Img-2596_mp4-18_jpg.rf.0863202bddb508751af5634bd9fa0cc6.jpg</path>
    <source>
        <database>Unknown</database>
    </source>
    <size>
        <width>640</width>
        <height>640</height>
        <depth>3</depth>
    </size>
    <segmented>0</segmented>
    <object>
        <name>note</name>
        <pose>Unspecified</pose>
        <truncated>0</truncated>
        <difficult>0</difficult>
        <bndbox>
            <xmin>144</xmin>
            <ymin>120</ymin>
            <xmax>523</xmax>
            <ymax>344</ymax>
        </bndbox>
    </object>
</annotation>
