<annotation>
    <folder>FRC2024</folder>
    <filename>VID_20240107_135442471_mp4-24_jpg.rf.c08c7881a00c055623a7f8d62d4d7cc5.jpg</filename>
    <path>/home/ubuntu/tensorflow_workspace/2024Game/data/FRC2024/VID_20240107_135442471_mp4-24_jpg.rf.c08c7881a00c055623a7f8d62d4d7cc5.jpg</path>
    <source>
        <database>Unknown</database>
    </source>
    <size>
        <width>640</width>
        <height>640</height>
        <depth>3</depth>
    </size>
    <segmented>0</segmented>
    <object>
        <name>note</name>
        <pose>Unspecified</pose>
        <truncated>0</truncated>
        <difficult>0</difficult>
        <bndbox>
            <xmin>102</xmin>
            <ymin>235</ymin>
            <xmax>213.5</xmax>
            <ymax>300.5</ymax>
        </bndbox>
    </object>
</annotation>
