<annotation>
    <folder>FRC2024</folder>
    <filename>WIN_20240106_16_21_28_Pro_mp4-24_jpg.rf.0d67a194a52f4d0637d0636536e84ba8.jpg</filename>
    <path>/home/ubuntu/tensorflow_workspace/2024Game/data/FRC2024/WIN_20240106_16_21_28_Pro_mp4-24_jpg.rf.0d67a194a52f4d0637d0636536e84ba8.jpg</path>
    <source>
        <database>Unknown</database>
    </source>
    <size>
        <width>640</width>
        <height>640</height>
        <depth>3</depth>
    </size>
    <segmented>0</segmented>
    <object>
        <name>note</name>
        <pose>Unspecified</pose>
        <truncated>0</truncated>
        <difficult>0</difficult>
        <bndbox>
            <xmin>154</xmin>
            <ymin>195</ymin>
            <xmax>312</xmax>
            <ymax>464.5</ymax>
        </bndbox>
    </object>
</annotation>
