<annotation verified="yes">
	<folder>FRC2024</folder>
	<filename>youtube-14_jpg.rf.d6c8037e87967dd8b16e1a40214719df.jpg</filename>
	<path>/home/ubuntu/tensorflow_workspace/2024Game/data/FRC2024/youtube-14_jpg.rf.d6c8037e87967dd8b16e1a40214719df.jpg</path>
	<source>
		<database>Unknown</database>
	</source>
	<size>
		<width>640</width>
		<height>640</height>
		<depth>3</depth>
	</size>
	<segmented>0</segmented>
	<object>
		<name>note</name>
		<pose>Unspecified</pose>
		<truncated>0</truncated>
		<difficult>0</difficult>
		<bndbox>
			<xmin>87</xmin>
			<ymin>62</ymin>
			<xmax>211</xmax>
			<ymax>291</ymax>
		</bndbox>
	</object>
</annotation>
