<annotation>
    <folder>FRC2024</folder>
    <filename>youtube-491_jpg.rf.30bc30c5e7678bb584eb55d55497f38d.jpg</filename>
    <path>/home/ubuntu/tensorflow_workspace/2024Game/data/FRC2024/youtube-491_jpg.rf.30bc30c5e7678bb584eb55d55497f38d.jpg</path>
    <source>
        <database>Unknown</database>
    </source>
    <size>
        <width>640</width>
        <height>640</height>
        <depth>3</depth>
    </size>
    <segmented>0</segmented>
    <object>
        <name>note</name>
        <pose>Unspecified</pose>
        <truncated>0</truncated>
        <difficult>0</difficult>
        <bndbox>
            <xmin>244</xmin>
            <ymin>172</ymin>
            <xmax>341.895</xmax>
            <ymax>312.041</ymax>
        </bndbox>
    </object>
</annotation>
