<annotation>
    <folder>FRC2024</folder>
    <filename>youtube-139_jpg.rf.ba6280d17fe6cfd3e1af5e65fd3fcfaa.jpg</filename>
    <path>/home/ubuntu/tensorflow_workspace/2024Game/data/FRC2024/youtube-139_jpg.rf.ba6280d17fe6cfd3e1af5e65fd3fcfaa.jpg</path>
    <source>
        <database>Unknown</database>
    </source>
    <size>
        <width>640</width>
        <height>640</height>
        <depth>3</depth>
    </size>
    <segmented>0</segmented>
    <object>
        <name>robot</name>
        <pose>Unspecified</pose>
        <truncated>0</truncated>
        <difficult>0</difficult>
        <bndbox>
            <xmin>305</xmin>
            <ymin>63</ymin>
            <xmax>329</xmax>
            <ymax>119.5</ymax>
        </bndbox>
    </object>    <object>
        <name>robot</name>
        <pose>Unspecified</pose>
        <truncated>0</truncated>
        <difficult>0</difficult>
        <bndbox>
            <xmin>442</xmin>
            <ymin>84</ymin>
            <xmax>493</xmax>
            <ymax>163</ymax>
        </bndbox>
    </object>
</annotation>
