<annotation verified="yes">
	<folder>videos</folder>
	<filename>20230318_085950.mp4_00908.png</filename>
	<path>/home/ubuntu/tensorflow_workspace/2023Game/data/videos/20230318_085950.mp4_00908.png</path>
	<source>
		<database>Unknown</database>
	</source>
	<size>
		<width>1920</width>
		<height>1080</height>
		<depth>3</depth>
	</size>
	<segmented>0</segmented>
	<object>
		<name>black_bottom_substation</name>
		<pose>Unspecified</pose>
		<truncated>0</truncated>
		<difficult>0</difficult>
		<bndbox>
			<xmin>1482</xmin>
			<ymin>204</ymin>
			<xmax>1519</xmax>
			<ymax>253</ymax>
		</bndbox>
	</object>
	<object>
		<name>black_bottom_substation</name>
		<pose>Unspecified</pose>
		<truncated>0</truncated>
		<difficult>0</difficult>
		<bndbox>
			<xmin>1367</xmin>
			<ymin>165</ymin>
			<xmax>1398</xmax>
			<ymax>211</ymax>
		</bndbox>
	</object>
	<object>
		<name>april_tag_7</name>
		<pose>Unspecified</pose>
		<truncated>0</truncated>
		<difficult>0</difficult>
		<bndbox>
			<xmin>1697</xmin>
			<ymin>21</ymin>
			<xmax>1757</xmax>
			<ymax>95</ymax>
		</bndbox>
	</object>
	<object>
		<name>black_bottom_substation</name>
		<pose>Unspecified</pose>
		<truncated>0</truncated>
		<difficult>0</difficult>
		<bndbox>
			<xmin>1846</xmin>
			<ymin>328</ymin>
			<xmax>1895</xmax>
			<ymax>385</ymax>
		</bndbox>
	</object>
	<object>
		<name>black_bottom_substation</name>
		<pose>Unspecified</pose>
		<truncated>0</truncated>
		<difficult>0</difficult>
		<bndbox>
			<xmin>1637</xmin>
			<ymin>254</ymin>
			<xmax>1674</xmax>
			<ymax>310</ymax>
		</bndbox>
	</object>
	<object>
		<name>black_bottom_substation</name>
		<pose>Unspecified</pose>
		<truncated>0</truncated>
		<difficult>0</difficult>
		<bndbox>
			<xmin>1263</xmin>
			<ymin>137</ymin>
			<xmax>1293</xmax>
			<ymax>178</ymax>
		</bndbox>
	</object>
	<object>
		<name>black_bottom_substation</name>
		<pose>Unspecified</pose>
		<truncated>0</truncated>
		<difficult>0</difficult>
		<bndbox>
			<xmin>1097</xmin>
			<ymin>84</ymin>
			<xmax>1116</xmax>
			<ymax>114</ymax>
		</bndbox>
	</object>
	<object>
		<name>black_bottom_substation</name>
		<pose>Unspecified</pose>
		<truncated>0</truncated>
		<difficult>0</difficult>
		<bndbox>
			<xmin>1183</xmin>
			<ymin>111</ymin>
			<xmax>1209</xmax>
			<ymax>136</ymax>
		</bndbox>
	</object>
	<object>
		<name>blue_tape_corners</name>
		<pose>Unspecified</pose>
		<truncated>0</truncated>
		<difficult>0</difficult>
		<bndbox>
			<xmin>863</xmin>
			<ymin>660</ymin>
			<xmax>981</xmax>
			<ymax>749</ymax>
		</bndbox>
	</object>
</annotation>
