<annotation verified="yes">
	<folder>videos</folder>
	<filename>20230401_085358.mp4_00152.png</filename>
	<path>/home/ubuntu/tensorflow_workspace/2023Game/data/videos/20230401_085358.mp4_00152.png</path>
	<source>
		<database>Unknown</database>
	</source>
	<size>
		<width>1920</width>
		<height>1080</height>
		<depth>3</depth>
	</size>
	<segmented>0</segmented>
	<object>
		<name>cone</name>
		<pose>Unspecified</pose>
		<truncated>0</truncated>
		<difficult>0</difficult>
		<bndbox>
			<xmin>1569</xmin>
			<ymin>301</ymin>
			<xmax>1660</xmax>
			<ymax>435</ymax>
		</bndbox>
	</object>
	<object>
		<name>cube</name>
		<pose>Unspecified</pose>
		<truncated>0</truncated>
		<difficult>0</difficult>
		<bndbox>
			<xmin>1751</xmin>
			<ymin>355</ymin>
			<xmax>1861</xmax>
			<ymax>452</ymax>
		</bndbox>
	</object>
	<object>
		<name>cone</name>
		<pose>Unspecified</pose>
		<truncated>0</truncated>
		<difficult>0</difficult>
		<bndbox>
			<xmin>1389</xmin>
			<ymin>291</ymin>
			<xmax>1470</xmax>
			<ymax>418</ymax>
		</bndbox>
	</object>
	<object>
		<name>cone</name>
		<pose>Unspecified</pose>
		<truncated>0</truncated>
		<difficult>0</difficult>
		<bndbox>
			<xmin>1202</xmin>
			<ymin>284</ymin>
			<xmax>1290</xmax>
			<ymax>402</ymax>
		</bndbox>
	</object>
	<object>
		<name>cone</name>
		<pose>Unspecified</pose>
		<truncated>0</truncated>
		<difficult>0</difficult>
		<bndbox>
			<xmin>1472</xmin>
			<ymin>296</ymin>
			<xmax>1548</xmax>
			<ymax>416</ymax>
		</bndbox>
	</object>
	<object>
		<name>cone</name>
		<pose>Unspecified</pose>
		<truncated>0</truncated>
		<difficult>0</difficult>
		<bndbox>
			<xmin>1666</xmin>
			<ymin>312</ymin>
			<xmax>1779</xmax>
			<ymax>451</ymax>
		</bndbox>
	</object>
	<object>
		<name>cone</name>
		<pose>Unspecified</pose>
		<truncated>0</truncated>
		<difficult>0</difficult>
		<bndbox>
			<xmin>1137</xmin>
			<ymin>275</ymin>
			<xmax>1230</xmax>
			<ymax>403</ymax>
		</bndbox>
	</object>
	<object>
		<name>cone</name>
		<pose>Unspecified</pose>
		<truncated>0</truncated>
		<difficult>0</difficult>
		<bndbox>
			<xmin>1294</xmin>
			<ymin>286</ymin>
			<xmax>1365</xmax>
			<ymax>406</ymax>
		</bndbox>
	</object>
	<object>
		<name>blue_tape_corners</name>
		<pose>Unspecified</pose>
		<truncated>0</truncated>
		<difficult>0</difficult>
		<bndbox>
			<xmin>1048</xmin>
			<ymin>223</ymin>
			<xmax>1126</xmax>
			<ymax>258</ymax>
		</bndbox>
	</object>
	<object>
		<name>red_tape_corners</name>
		<pose>Unspecified</pose>
		<truncated>0</truncated>
		<difficult>0</difficult>
		<bndbox>
			<xmin>1701</xmin>
			<ymin>594</ymin>
			<xmax>1832</xmax>
			<ymax>665</ymax>
		</bndbox>
	</object>
	<object>
		<name>red_tape_corners</name>
		<pose>Unspecified</pose>
		<truncated>0</truncated>
		<difficult>0</difficult>
		<bndbox>
			<xmin>242</xmin>
			<ymin>434</ymin>
			<xmax>381</xmax>
			<ymax>489</ymax>
		</bndbox>
	</object>
	<object>
		<name>red_tape_corners</name>
		<pose>Unspecified</pose>
		<truncated>0</truncated>
		<difficult>0</difficult>
		<bndbox>
			<xmin>567</xmin>
			<ymin>216</ymin>
			<xmax>637</xmax>
			<ymax>280</ymax>
		</bndbox>
	</object>
</annotation>
