<annotation>
	<folder>videos</folder>
	<filename>ncash2023_gopro3.mp4_01755.png</filename>
	<path>/home/ubuntu/tensorflow_workspace/2023Game/data/videos/ncash2023_gopro3.mp4_01755.png</path>
	<source>
		<database>Unknown</database>
	</source>
	<size>
		<width>1920</width>
		<height>1440</height>
		<depth>3</depth>
	</size>
	<segmented>0</segmented>
	<object>
		<name>red_ds_number</name>
		<pose>Unspecified</pose>
		<truncated>0</truncated>
		<difficult>0</difficult>
		<bndbox>
			<xmin>1466</xmin>
			<ymin>175</ymin>
			<xmax>1555</xmax>
			<ymax>208</ymax>
		</bndbox>
	</object>
	<object>
		<name>red_ds_number</name>
		<pose>Unspecified</pose>
		<truncated>0</truncated>
		<difficult>0</difficult>
		<bndbox>
			<xmin>1219</xmin>
			<ymin>140</ymin>
			<xmax>1304</xmax>
			<ymax>168</ymax>
		</bndbox>
	</object>
	<object>
		<name>red_robot</name>
		<pose>Unspecified</pose>
		<truncated>0</truncated>
		<difficult>0</difficult>
		<bndbox>
			<xmin>819</xmin>
			<ymin>232</ymin>
			<xmax>1084</xmax>
			<ymax>537</ymax>
		</bndbox>
	</object>
	<object>
		<name>red_ds_light</name>
		<pose>Unspecified</pose>
		<truncated>0</truncated>
		<difficult>0</difficult>
		<bndbox>
			<xmin>1441</xmin>
			<ymin>166</ymin>
			<xmax>1462</xmax>
			<ymax>204</ymax>
		</bndbox>
	</object>
	<object>
		<name>red_ds_light</name>
		<pose>Unspecified</pose>
		<truncated>0</truncated>
		<difficult>0</difficult>
		<bndbox>
			<xmin>1195</xmin>
			<ymin>133</ymin>
			<xmax>1220</xmax>
			<ymax>165</ymax>
		</bndbox>
	</object>
	<object>
		<name>red_ds_number</name>
		<pose>Unspecified</pose>
		<truncated>0</truncated>
		<difficult>0</difficult>
		<bndbox>
			<xmin>1716</xmin>
			<ymin>238</ymin>
			<xmax>1777</xmax>
			<ymax>265</ymax>
		</bndbox>
	</object>
	<object>
		<name>red_ds_number</name>
		<pose>Unspecified</pose>
		<truncated>0</truncated>
		<difficult>0</difficult>
		<bndbox>
			<xmin>1359</xmin>
			<ymin>158</ymin>
			<xmax>1436</xmax>
			<ymax>183</ymax>
		</bndbox>
	</object>
	<object>
		<name>blue_tape_corner</name>
		<pose>Unspecified</pose>
		<truncated>0</truncated>
		<difficult>0</difficult>
		<bndbox>
			<xmin>655</xmin>
			<ymin>413</ymin>
			<xmax>697</xmax>
			<ymax>444</ymax>
		</bndbox>
	</object>
	<object>
		<name>red_tape_corner</name>
		<pose>Unspecified</pose>
		<truncated>0</truncated>
		<difficult>0</difficult>
		<bndbox>
			<xmin>1044</xmin>
			<ymin>590</ymin>
			<xmax>1127</xmax>
			<ymax>668</ymax>
		</bndbox>
	</object>
	<object>
		<name>red_ds_light</name>
		<pose>Unspecified</pose>
		<truncated>0</truncated>
		<difficult>0</difficult>
		<bndbox>
			<xmin>1688</xmin>
			<ymin>229</ymin>
			<xmax>1704</xmax>
			<ymax>261</ymax>
		</bndbox>
	</object>
</annotation>
