<annotation>
	<folder>Field_Photo_Survey_01</folder>
	<filename>IMG_5734.JPG</filename>
	<path>/home/ubuntu/tensorflow_workspace/2019Game/data/videos/IMG_5734.JPG</path>
	<source>
		<database>Unknown</database>
	</source>
	<size>
		<width>4000</width>
		<height>3000</height>
		<depth>3</depth>
	</size>
	<segmented>0</segmented>
	<object>
		<name>red_ds_number</name>
		<pose>Unspecified</pose>
		<truncated>0</truncated>
		<difficult>0</difficult>
		<bndbox>
			<xmin>1117</xmin>
			<ymin>733</ymin>
			<xmax>1191</xmax>
			<ymax>761</ymax>
		</bndbox>
	</object>
	<object>
		<name>red_ds_number</name>
		<pose>Unspecified</pose>
		<truncated>0</truncated>
		<difficult>0</difficult>
		<bndbox>
			<xmin>1254</xmin>
			<ymin>731</ymin>
			<xmax>1342</xmax>
			<ymax>769</ymax>
		</bndbox>
	</object>
	<object>
		<name>ds_light</name>
		<pose>Unspecified</pose>
		<truncated>0</truncated>
		<difficult>0</difficult>
		<bndbox>
			<xmin>1389</xmin>
			<ymin>738</ymin>
			<xmax>1401</xmax>
			<ymax>773</ymax>
		</bndbox>
	</object>
	<object>
		<name>red_ds_number</name>
		<pose>Unspecified</pose>
		<truncated>0</truncated>
		<difficult>0</difficult>
		<bndbox>
			<xmin>1452</xmin>
			<ymin>731</ymin>
			<xmax>1525</xmax>
			<ymax>763</ymax>
		</bndbox>
	</object>
	<object>
		<name>red_ds_number</name>
		<pose>Unspecified</pose>
		<truncated>0</truncated>
		<difficult>0</difficult>
		<bndbox>
			<xmin>1793</xmin>
			<ymin>733</ymin>
			<xmax>1861</xmax>
			<ymax>756</ymax>
		</bndbox>
	</object>
</annotation>
