<annotation verified="yes">
	<folder>videos</folder>
	<filename>IMG_6089.JPG</filename>
	<path>/home/ubuntu/tensorflow_workspace/2019Game/data/videos/IMG_6089.JPG</path>
	<source>
		<database>Unknown</database>
	</source>
	<size>
		<width>4000</width>
		<height>3000</height>
		<depth>3</depth>
	</size>
	<segmented>0</segmented>
	<object>
		<name>blue_rocket_top</name>
		<pose>Unspecified</pose>
		<truncated>0</truncated>
		<difficult>0</difficult>
		<bndbox>
			<xmin>1478</xmin>
			<ymin>614</ymin>
			<xmax>2222</xmax>
			<ymax>797</ymax>
		</bndbox>
	</object>
	<object>
		<name>rocket_cargo_hole</name>
		<pose>Unspecified</pose>
		<truncated>0</truncated>
		<difficult>0</difficult>
		<bndbox>
			<xmin>1241</xmin>
			<ymin>1067</ymin>
			<xmax>2411</xmax>
			<ymax>2233</ymax>
		</bndbox>
	</object>
	<object>
		<name>rocket_hatch_hole</name>
		<pose>Unspecified</pose>
		<truncated>0</truncated>
		<difficult>0</difficult>
		<bndbox>
			<xmin>2572</xmin>
			<ymin>1883</ymin>
			<xmax>2933</xmax>
			<ymax>2644</ymax>
		</bndbox>
	</object>
	<object>
		<name>rocket_hatch_hole</name>
		<pose>Unspecified</pose>
		<truncated>0</truncated>
		<difficult>0</difficult>
		<bndbox>
			<xmin>794</xmin>
			<ymin>1867</ymin>
			<xmax>1116</xmax>
			<ymax>2650</ymax>
		</bndbox>
	</object>
</annotation>
