<annotation>
	<folder>videos</folder>
	<filename>DSC01685.JPG</filename>
	<path>/home/ubuntu/tensorflow_workspace/2022Game/data/videos/DSC01685.JPG</path>
	<source>
		<database>Unknown</database>
	</source>
	<size>
		<width>6000</width>
		<height>4000</height>
		<depth>3</depth>
	</size>
	<segmented>0</segmented>
	<object>
		<name>purple_tape</name>
		<pose>Unspecified</pose>
		<truncated>0</truncated>
		<difficult>0</difficult>
		<bndbox>
			<xmin>3159</xmin>
			<ymin>2843</ymin>
			<xmax>3426</xmax>
			<ymax>2947</ymax>
		</bndbox>
	</object>
	<object>
		<name>purple_tape</name>
		<pose>Unspecified</pose>
		<truncated>0</truncated>
		<difficult>0</difficult>
		<bndbox>
			<xmin>2388</xmin>
			<ymin>3114</ymin>
			<xmax>2716</xmax>
			<ymax>3252</ymax>
		</bndbox>
	</object>
	<object>
		<name>purple_tape</name>
		<pose>Unspecified</pose>
		<truncated>0</truncated>
		<difficult>0</difficult>
		<bndbox>
			<xmin>2807</xmin>
			<ymin>2986</ymin>
			<xmax>3064</xmax>
			<ymax>3086</ymax>
		</bndbox>
	</object>
	<object>
		<name>purple_tape</name>
		<pose>Unspecified</pose>
		<truncated>0</truncated>
		<difficult>0</difficult>
		<bndbox>
			<xmin>3507</xmin>
			<ymin>2709</ymin>
			<xmax>3783</xmax>
			<ymax>2819</ymax>
		</bndbox>
	</object>
	<object>
		<name>purple_tape</name>
		<pose>Unspecified</pose>
		<truncated>0</truncated>
		<difficult>0</difficult>
		<bndbox>
			<xmin>3831</xmin>
			<ymin>2567</ymin>
			<xmax>4107</xmax>
			<ymax>2662</ymax>
		</bndbox>
	</object>
	<object>
		<name>purple_tape</name>
		<pose>Unspecified</pose>
		<truncated>0</truncated>
		<difficult>0</difficult>
		<bndbox>
			<xmin>1907</xmin>
			<ymin>3252</ymin>
			<xmax>2240</xmax>
			<ymax>3419</ymax>
		</bndbox>
	</object>
	<object>
		<name>purple_tape</name>
		<pose>Unspecified</pose>
		<truncated>0</truncated>
		<difficult>0</difficult>
		<bndbox>
			<xmin>4145</xmin>
			<ymin>2514</ymin>
			<xmax>4264</xmax>
			<ymax>2533</ymax>
		</bndbox>
	</object>
</annotation>
