<annotation verified="yes">
	<folder>videos</folder>
	<filename>FRCTwitchVision.mp4_22200.png</filename>
	<path>/home/ubuntu/tensorflow_workspace/2022Game/data/videos/FRCTwitchVision.mp4_22200.png</path>
	<source>
		<database>Unknown</database>
	</source>
	<size>
		<width>1920</width>
		<height>1080</height>
		<depth>3</depth>
	</size>
	<segmented>0</segmented>
	<object>
		<name>blue_launchpad</name>
		<pose>Unspecified</pose>
		<truncated>0</truncated>
		<difficult>0</difficult>
		<bndbox>
			<xmin>1238</xmin>
			<ymin>525</ymin>
			<xmax>1270</xmax>
			<ymax>587</ymax>
		</bndbox>
	</object>
	<object>
		<name>blue_truss_segment</name>
		<pose>Unspecified</pose>
		<truncated>0</truncated>
		<difficult>0</difficult>
		<bndbox>
			<xmin>1257</xmin>
			<ymin>417</ymin>
			<xmax>1300</xmax>
			<ymax>461</ymax>
		</bndbox>
	</object>
	<object>
		<name>blue_cargo</name>
		<pose>Unspecified</pose>
		<truncated>0</truncated>
		<difficult>0</difficult>
		<bndbox>
			<xmin>1147</xmin>
			<ymin>705</ymin>
			<xmax>1188</xmax>
			<ymax>737</ymax>
		</bndbox>
	</object>
	<object>
		<name>blue_cargo_starting_position</name>
		<pose>Unspecified</pose>
		<truncated>0</truncated>
		<difficult>0</difficult>
		<bndbox>
			<xmin>1129</xmin>
			<ymin>720</ymin>
			<xmax>1140</xmax>
			<ymax>734</ymax>
		</bndbox>
	</object>
	<object>
		<name>red_cargo</name>
		<pose>Unspecified</pose>
		<truncated>0</truncated>
		<difficult>0</difficult>
		<bndbox>
			<xmin>1136</xmin>
			<ymin>672</ymin>
			<xmax>1174</xmax>
			<ymax>701</ymax>
		</bndbox>
	</object>
	<object>
		<name>red_cargo_starting_position</name>
		<pose>Unspecified</pose>
		<truncated>0</truncated>
		<difficult>0</difficult>
		<bndbox>
			<xmin>962</xmin>
			<ymin>483</ymin>
			<xmax>974</xmax>
			<ymax>495</ymax>
		</bndbox>
	</object>
	<object>
		<name>blue_cargo_starting_position</name>
		<pose>Unspecified</pose>
		<truncated>0</truncated>
		<difficult>0</difficult>
		<bndbox>
			<xmin>831</xmin>
			<ymin>433</ymin>
			<xmax>846</xmax>
			<ymax>442</ymax>
		</bndbox>
	</object>
	<object>
		<name>blue_truss_segment</name>
		<pose>Unspecified</pose>
		<truncated>0</truncated>
		<difficult>0</difficult>
		<bndbox>
			<xmin>1594</xmin>
			<ymin>613</ymin>
			<xmax>1646</xmax>
			<ymax>667</ymax>
		</bndbox>
	</object>
	<object>
		<name>blue_launchpad</name>
		<pose>Unspecified</pose>
		<truncated>0</truncated>
		<difficult>0</difficult>
		<bndbox>
			<xmin>1535</xmin>
			<ymin>722</ymin>
			<xmax>1580</xmax>
			<ymax>804</ymax>
		</bndbox>
	</object>
	<object>
		<name>red_tape_corners</name>
		<pose>Unspecified</pose>
		<truncated>0</truncated>
		<difficult>0</difficult>
		<bndbox>
			<xmin>570</xmin>
			<ymin>784</ymin>
			<xmax>604</xmax>
			<ymax>813</ymax>
		</bndbox>
	</object>
	<object>
		<name>red_tape_corners</name>
		<pose>Unspecified</pose>
		<truncated>0</truncated>
		<difficult>0</difficult>
		<bndbox>
			<xmin>386</xmin>
			<ymin>801</ymin>
			<xmax>428</xmax>
			<ymax>824</ymax>
		</bndbox>
	</object>
	<object>
		<name>blue_tape_corners</name>
		<pose>Unspecified</pose>
		<truncated>0</truncated>
		<difficult>0</difficult>
		<bndbox>
			<xmin>671</xmin>
			<ymin>617</ymin>
			<xmax>692</xmax>
			<ymax>634</ymax>
		</bndbox>
	</object>
	<object>
		<name>terminal_base_corner</name>
		<pose>Unspecified</pose>
		<truncated>0</truncated>
		<difficult>0</difficult>
		<bndbox>
			<xmin>1239</xmin>
			<ymin>342</ymin>
			<xmax>1253</xmax>
			<ymax>357</ymax>
		</bndbox>
	</object>
	<object>
		<name>guardrail_intersect</name>
		<pose>Unspecified</pose>
		<truncated>0</truncated>
		<difficult>0</difficult>
		<bndbox>
			<xmin>948</xmin>
			<ymin>285</ymin>
			<xmax>961</xmax>
			<ymax>297</ymax>
		</bndbox>
	</object>
	<object>
		<name>guardrail_intersect</name>
		<pose>Unspecified</pose>
		<truncated>0</truncated>
		<difficult>0</difficult>
		<bndbox>
			<xmin>722</xmin>
			<ymin>330</ymin>
			<xmax>739</xmax>
			<ymax>341</ymax>
		</bndbox>
	</object>
	<object>
		<name>hub_fender_corner</name>
		<pose>Unspecified</pose>
		<truncated>0</truncated>
		<difficult>0</difficult>
		<bndbox>
			<xmin>686</xmin>
			<ymin>532</ymin>
			<xmax>727</xmax>
			<ymax>563</ymax>
		</bndbox>
	</object>
	<object>
		<name>hub_fender_corner</name>
		<pose>Unspecified</pose>
		<truncated>0</truncated>
		<difficult>0</difficult>
		<bndbox>
			<xmin>287</xmin>
			<ymin>758</ymin>
			<xmax>322</xmax>
			<ymax>778</ymax>
		</bndbox>
	</object>
	<object>
		<name>hub_fender_corner</name>
		<pose>Unspecified</pose>
		<truncated>0</truncated>
		<difficult>0</difficult>
		<bndbox>
			<xmin>268</xmin>
			<ymin>727</ymin>
			<xmax>297</xmax>
			<ymax>748</ymax>
		</bndbox>
	</object>
	<object>
		<name>rapid_react_hub_logo</name>
		<pose>Unspecified</pose>
		<truncated>0</truncated>
		<difficult>0</difficult>
		<bndbox>
			<xmin>443</xmin>
			<ymin>740</ymin>
			<xmax>547</xmax>
			<ymax>786</ymax>
		</bndbox>
	</object>
	<object>
		<name>terminal_base_corner</name>
		<pose>Unspecified</pose>
		<truncated>0</truncated>
		<difficult>0</difficult>
		<bndbox>
			<xmin>990</xmin>
			<ymin>317</ymin>
			<xmax>1009</xmax>
			<ymax>326</ymax>
		</bndbox>
	</object>
	<object>
		<name>black_tape_intersect</name>
		<pose>Unspecified</pose>
		<truncated>0</truncated>
		<difficult>0</difficult>
		<bndbox>
			<xmin>1336</xmin>
			<ymin>541</ymin>
			<xmax>1375</xmax>
			<ymax>573</ymax>
		</bndbox>
	</object>
	<object>
		<name>blue_black_tape_intersect</name>
		<pose>Unspecified</pose>
		<truncated>0</truncated>
		<difficult>0</difficult>
		<bndbox>
			<xmin>871</xmin>
			<ymin>553</ymin>
			<xmax>929</xmax>
			<ymax>593</ymax>
		</bndbox>
	</object>
	<object>
		<name>blue_tape_corners</name>
		<pose>Unspecified</pose>
		<truncated>0</truncated>
		<difficult>0</difficult>
		<bndbox>
			<xmin>947</xmin>
			<ymin>638</ymin>
			<xmax>995</xmax>
			<ymax>689</ymax>
		</bndbox>
	</object>
	<object>
		<name>blue_tape_corners</name>
		<pose>Unspecified</pose>
		<truncated>0</truncated>
		<difficult>0</difficult>
		<bndbox>
			<xmin>826</xmin>
			<ymin>507</ymin>
			<xmax>878</xmax>
			<ymax>538</ymax>
		</bndbox>
	</object>
	<object>
		<name>blue_tape_corners</name>
		<pose>Unspecified</pose>
		<truncated>0</truncated>
		<difficult>0</difficult>
		<bndbox>
			<xmin>760</xmin>
			<ymin>481</ymin>
			<xmax>824</xmax>
			<ymax>517</ymax>
		</bndbox>
	</object>
	<object>
		<name>red_black_tape_intersect</name>
		<pose>Unspecified</pose>
		<truncated>0</truncated>
		<difficult>0</difficult>
		<bndbox>
			<xmin>5</xmin>
			<ymin>833</ymin>
			<xmax>45</xmax>
			<ymax>874</ymax>
		</bndbox>
	</object>
	<object>
		<name>blue_cargo</name>
		<pose>Unspecified</pose>
		<truncated>0</truncated>
		<difficult>0</difficult>
		<bndbox>
			<xmin>182</xmin>
			<ymin>512</ymin>
			<xmax>213</xmax>
			<ymax>549</ymax>
		</bndbox>
	</object>
</annotation>
