<annotation verified="yes">
	<folder>videos</folder>
	<filename>FRCTwitchVision.mp4_14220.png</filename>
	<path>/home/ubuntu/tensorflow_workspace/2022Game/data/videos/FRCTwitchVision.mp4_14220.png</path>
	<source>
		<database>Unknown</database>
	</source>
	<size>
		<width>1920</width>
		<height>1080</height>
		<depth>3</depth>
	</size>
	<segmented>0</segmented>
	<object>
		<name>red_tape_corners</name>
		<pose>Unspecified</pose>
		<truncated>0</truncated>
		<difficult>0</difficult>
		<bndbox>
			<xmin>564</xmin>
			<ymin>583</ymin>
			<xmax>635</xmax>
			<ymax>645</ymax>
		</bndbox>
	</object>
	<object>
		<name>red_tape_corners</name>
		<pose>Unspecified</pose>
		<truncated>0</truncated>
		<difficult>0</difficult>
		<bndbox>
			<xmin>359</xmin>
			<ymin>769</ymin>
			<xmax>412</xmax>
			<ymax>822</ymax>
		</bndbox>
	</object>
	<object>
		<name>red_tape_corners</name>
		<pose>Unspecified</pose>
		<truncated>0</truncated>
		<difficult>0</difficult>
		<bndbox>
			<xmin>1702</xmin>
			<ymin>990</ymin>
			<xmax>1755</xmax>
			<ymax>1060</ymax>
		</bndbox>
	</object>
	<object>
		<name>blue_tape_corners</name>
		<pose>Unspecified</pose>
		<truncated>0</truncated>
		<difficult>0</difficult>
		<bndbox>
			<xmin>1546</xmin>
			<ymin>651</ymin>
			<xmax>1590</xmax>
			<ymax>694</ymax>
		</bndbox>
	</object>
	<object>
		<name>blue_tape_corners</name>
		<pose>Unspecified</pose>
		<truncated>0</truncated>
		<difficult>0</difficult>
		<bndbox>
			<xmin>1262</xmin>
			<ymin>524</ymin>
			<xmax>1306</xmax>
			<ymax>564</ymax>
		</bndbox>
	</object>
	<object>
		<name>blue_tape_corners</name>
		<pose>Unspecified</pose>
		<truncated>0</truncated>
		<difficult>0</difficult>
		<bndbox>
			<xmin>1704</xmin>
			<ymin>921</ymin>
			<xmax>1767</xmax>
			<ymax>971</ymax>
		</bndbox>
	</object>
	<object>
		<name>blue_tape_corners</name>
		<pose>Unspecified</pose>
		<truncated>0</truncated>
		<difficult>0</difficult>
		<bndbox>
			<xmin>642</xmin>
			<ymin>557</ymin>
			<xmax>688</xmax>
			<ymax>581</ymax>
		</bndbox>
	</object>
	<object>
		<name>ds_numbers</name>
		<pose>Unspecified</pose>
		<truncated>0</truncated>
		<difficult>0</difficult>
		<bndbox>
			<xmin>1725</xmin>
			<ymin>196</ymin>
			<xmax>1793</xmax>
			<ymax>225</ymax>
		</bndbox>
	</object>
	<object>
		<name>blue_ds_light</name>
		<pose>Unspecified</pose>
		<truncated>0</truncated>
		<difficult>0</difficult>
		<bndbox>
			<xmin>1704</xmin>
			<ymin>193</ymin>
			<xmax>1719</xmax>
			<ymax>218</ymax>
		</bndbox>
	</object>
	<object>
		<name>red_tape_corners</name>
		<pose>Unspecified</pose>
		<truncated>0</truncated>
		<difficult>0</difficult>
		<bndbox>
			<xmin>1175</xmin>
			<ymin>825</ymin>
			<xmax>1238</xmax>
			<ymax>864</ymax>
		</bndbox>
	</object>
	<object>
		<name>red_tape_corners</name>
		<pose>Unspecified</pose>
		<truncated>0</truncated>
		<difficult>0</difficult>
		<bndbox>
			<xmin>938</xmin>
			<ymin>852</ymin>
			<xmax>1012</xmax>
			<ymax>872</ymax>
		</bndbox>
	</object>
	</annotation>